midsv/__init__.py
midsv/converter.py
midsv/formatter.py
midsv/io.py
midsv/main.py
midsv/polisher.py
midsv/validator.py
midsv-0.13.1.dist-info/METADATA
midsv-0.13.1.dist-info/WHEEL
midsv-0.13.1.dist-info/licenses/LICENSE
midsv-0.13.1.dist-info/RECORD
