Metadata-Version: 2.4
Name: midsv
Version: 0.13.1
Summary: Python module to convert SAM to MIDSV format.
License: MIT
License-File: LICENSE
Author: Akihiro Kuno
Author-email: akuno@md.tsukuba.ac.jp
Requires-Python: >=3.10,<4.0
Classifier: Intended Audience :: Science/Research
Classifier: License :: OSI Approved :: MIT License
Classifier: Operating System :: OS Independent
Classifier: Programming Language :: Python :: 3
Classifier: Programming Language :: Python :: 3.10
Classifier: Programming Language :: Python :: 3.11
Classifier: Programming Language :: Python :: 3.12
Classifier: Programming Language :: Python :: 3.13
Classifier: Programming Language :: Python :: 3.14
Classifier: Topic :: Scientific/Engineering :: Bio-Informatics
Project-URL: Homepage, https://github.com/akikuno/midsv
Project-URL: Repository, https://github.com/akikuno/midsv
